opentrons/__init__.py
opentrons/_version.py
opentrons/execute.py
opentrons/legacy_broker.py
opentrons/ordered_set.py
opentrons/py.typed
opentrons/simulate.py
opentrons/types.py
opentrons/calibration_storage/__init__.py
opentrons/calibration_storage/deck_configuration.py
opentrons/calibration_storage/encoder_decoder.py
opentrons/calibration_storage/file_operators.py
opentrons/calibration_storage/helpers.py
opentrons/calibration_storage/types.py
opentrons/calibration_storage/ot2/__init__.py
opentrons/calibration_storage/ot2/deck_attitude.py
opentrons/calibration_storage/ot2/mark_bad_calibration.py
opentrons/calibration_storage/ot2/pipette_offset.py
opentrons/calibration_storage/ot2/tip_length.py
opentrons/calibration_storage/ot2/models/__init__.py
opentrons/calibration_storage/ot2/models/v1.py
opentrons/calibration_storage/ot3/__init__.py
opentrons/calibration_storage/ot3/deck_attitude.py
opentrons/calibration_storage/ot3/gripper_offset.py
opentrons/calibration_storage/ot3/module_offset.py
opentrons/calibration_storage/ot3/pipette_offset.py
opentrons/calibration_storage/ot3/models/__init__.py
opentrons/calibration_storage/ot3/models/v1.py
opentrons/cli/__init__.py
opentrons/cli/__main__.py
opentrons/cli/analyze.py
opentrons/config/__init__.py
opentrons/config/advanced_settings.py
opentrons/config/defaults_ot2.py
opentrons/config/defaults_ot3.py
opentrons/config/feature_flags.py
opentrons/config/gripper_config.py
opentrons/config/reset.py
opentrons/config/robot_configs.py
opentrons/config/types.py
opentrons/drivers/__init__.py
opentrons/drivers/command_builder.py
opentrons/drivers/serial_communication.py
opentrons/drivers/types.py
opentrons/drivers/utils.py
opentrons/drivers/absorbance_reader/__init__.py
opentrons/drivers/absorbance_reader/abstract.py
opentrons/drivers/absorbance_reader/async_byonoy.py
opentrons/drivers/absorbance_reader/driver.py
opentrons/drivers/absorbance_reader/hid_protocol.py
opentrons/drivers/absorbance_reader/simulator.py
opentrons-8.7.0.dist-info/METADATA
opentrons-8.7.0.dist-info/WHEEL
opentrons-8.7.0.dist-info/entry_points.txt
opentrons-8.7.0.dist-info/licenses/LICENSE
opentrons-8.7.0.dist-info/RECORD
